itsjustcode/__init__.py
itsjustcode/language.py
itsjustcode/strutils.py
itsjustcode-0.3.dist-info/LICENSE
itsjustcode-0.3.dist-info/METADATA
itsjustcode-0.3.dist-info/WHEEL
itsjustcode-0.3.dist-info/top_level.txt
itsjustcode-0.3.dist-info/RECORD
